sqlalchemy_fulltext/__init__.py
sqlalchemy_fulltext/modes.py
SQLAlchemy_FullText_Search_Ngram-0.1.1.dist-info/LICENSE
SQLAlchemy_FullText_Search_Ngram-0.1.1.dist-info/METADATA
SQLAlchemy_FullText_Search_Ngram-0.1.1.dist-info/WHEEL
SQLAlchemy_FullText_Search_Ngram-0.1.1.dist-info/top_level.txt
SQLAlchemy_FullText_Search_Ngram-0.1.1.dist-info/RECORD
